bioCaption/__init__.py
bioCaption/configuration.py
bioCaption/default_config.py
bioCaption/data/__init__.py
bioCaption/data/downloads.py
bioCaption/models/__init__.py
bioCaption/models/captionModels/__init__.py
bioCaption/models/captionModels/baselines.py
bioCaption/models/captionModels/caption_models_evaluation.py
bioCaption/models/captionModels/utils.py
bioCaption/models/tagModels/__init__.py
bioCaption/models/tagModels/chexnet.py
bioCaption/models/tagModels/knn.py
bioCaption/models/tagModels/tag_models_evaluation.py
bioCaption-1.1.1.dist-info/METADATA
bioCaption-1.1.1.dist-info/RECORD
bioCaption-1.1.1.dist-info/WHEEL
bioCaption-1.1.1.dist-info/top_level.txt
test_bioCaption/__init__.py
