Metadata-Version: 2.1
Name: bioCaption
Version: 1.1.1
Summary: Diagnostic Captioning
Home-page: https://github.com/nlpaueb/dc
Author: nlpaueb
License: UNKNOWN
Keywords: diagnostic image captioning machine learning
Platform: UNKNOWN
Classifier: Development Status :: 3 - Alpha
Classifier: License :: OSI Approved :: MIT License
Classifier: Programming Language :: Python :: 3.7
Requires-Python: >=3.6
Requires-Dist: bs4
